django_in_request_cache/__init__.py
django_in_request_cache/cache.py
django_in_request_cache-0.0.6.dist-info/top_level.txt
django_in_request_cache-0.0.6.dist-info/METADATA
django_in_request_cache-0.0.6.dist-info/DESCRIPTION.rst
django_in_request_cache-0.0.6.dist-info/LICENSE.txt
django_in_request_cache-0.0.6.dist-info/metadata.json
django_in_request_cache-0.0.6.dist-info/WHEEL
django_in_request_cache-0.0.6.dist-info/RECORD
