Metadata-Version: 2.0
Name: django-in-request-cache
Version: 0.0.6
Summary: Django cache backend stored in django request
Home-page: https://github.com/mojeto/django-in-request-cache
Author: Jan Nakladal
Author-email: mojeto1@gmail.com
License: MIT
Platform: UNKNOWN
Classifier: Development Status :: 2 - Pre-Alpha
Classifier: Environment :: Web Environment
Classifier: Framework :: Django
Classifier: Intended Audience :: Developers
Classifier: Operating System :: OS Independent
Classifier: Programming Language :: Python
Classifier: Programming Language :: Python :: 2.7
Classifier: Programming Language :: Python :: 3.5
Requires-Dist: Django (>=1.6)
Requires-Dist: django-globals (>=0.2)
